markpickle/__init__.py
markpickle/__main__.py
markpickle/atx_as_dictionary.py
markpickle/binary_streams.py
markpickle/cli.py
markpickle/config_class.py
markpickle/deserialize.py
markpickle/meta.py
markpickle/mypy_types.py
markpickle/py.typed
markpickle/python_to_tables.py
markpickle/serialize.py
markpickle/simplify_types.py
markpickle/split_file_code.py
markpickle/sugar.py
markpickle/third_party_tables.py
markpickle/tool.py
markpickle/unicode_formatting.py
markpickle-1.6.1.dist-info/LICENSE
markpickle-1.6.1.dist-info/METADATA
markpickle-1.6.1.dist-info/WHEEL
markpickle-1.6.1.dist-info/RECORD
